dirmap_next/__init__.py
dirmap_next/dirmap.conf
dirmap_next/dirmap.py
dirmap_next/py.typed
dirmap_next/data/crawl_mode_suffix.txt
dirmap_next/data/dict_mode_dict.txt
dirmap_next/data/fuzz_mode_dir.txt
dirmap_next/data/fuzz_mode_ext.txt
dirmap_next/data/user_agents.txt
dirmap_next/data/dictmult/BAK.min.txt
dirmap_next/data/dictmult/BAK.txt
dirmap_next/data/dictmult/LEAKS.txt
dirmap_next/data/fuzzmult/fuzz_mode_dir.txt
dirmap_next/data/fuzzmult/fuzz_mode_ext.txt
dirmap_next/lib/__init__.py
dirmap_next/lib/controller/__init__.py
dirmap_next/lib/controller/bruter.py
dirmap_next/lib/controller/engine.py
dirmap_next/lib/core/__init__.py
dirmap_next/lib/core/common.py
dirmap_next/lib/core/data.py
dirmap_next/lib/core/datatype.py
dirmap_next/lib/core/enums.py
dirmap_next/lib/core/option.py
dirmap_next/lib/core/setting.py
dirmap_next/lib/parse/__init__.py
dirmap_next/lib/parse/cmdline.py
dirmap_next/lib/plugins/__init__.py
dirmap_next/lib/plugins/inspector.py
dirmap_next/lib/utils/__init__.py
dirmap_next/lib/utils/config.py
dirmap_next/lib/utils/console.py
dirmap_next/thirdlib/IPy/.gitignore
dirmap_next/thirdlib/IPy/AUTHORS
dirmap_next/thirdlib/IPy/COPYING
dirmap_next/thirdlib/IPy/ChangeLog
dirmap_next/thirdlib/IPy/IPy.py
dirmap_next/thirdlib/IPy/MANIFEST.in
dirmap_next/thirdlib/IPy/Makefile
dirmap_next/thirdlib/IPy/README
dirmap_next/thirdlib/IPy/setup.py
dirmap_next/thirdlib/IPy/test_doc.py
dirmap_next/thirdlib/IPy/example/confbuilder
dirmap_next/thirdlib/IPy/example/confbuilder.py
dirmap_next/thirdlib/IPy/test/test.rst
dirmap_next/thirdlib/IPy/test/test_IPy.py
dirmap_next/thirdlib/IPy/test/test_fuzz.py
dirmap_next/thirdlib/colorama/__init__.py
dirmap_next/thirdlib/colorama/ansi.py
dirmap_next/thirdlib/colorama/ansitowin32.py
dirmap_next/thirdlib/colorama/initialise.py
dirmap_next/thirdlib/colorama/win32.py
dirmap_next/thirdlib/colorama/winterm.py
dirmap_next-25.12.23.dist-info/METADATA
dirmap_next-25.12.23.dist-info/WHEEL
dirmap_next-25.12.23.dist-info/entry_points.txt
dirmap_next-25.12.23.dist-info/licenses/LICENSE
dirmap_next-25.12.23.dist-info/RECORD
