Metadata-Version: 2.4
Name: dirmap-next
Version: 25.12.23
Summary: https://github.com/H4ckForJob/dirmap; thank h4ckforfun
Author-email: LIghtJUNction <LIghtJUNction.me@gmail.com>, h4ckforfun <xxlin.ujs@qq.com>
License-File: LICENSE
Requires-Python: >=3.12
Requires-Dist: gevent>=25.4.1
Requires-Dist: lxml>=5.3.2
Requires-Dist: progressbar2>=4.5.0
Requires-Dist: requests>=2.32.3
